<annotation>
	<folder>dataset_toy_story</folder>
	<filename>image33.png</filename>
	<path>/home/ctortosam/Escritorio/dataset_toy_story/image33.png</path>
	<source>
		<database>Unknown</database>
	</source>
	<size>
		<width>391</width>
		<height>339</height>
		<depth>3</depth>
	</size>
	<segmented>0</segmented>
	<object>
		<name>toy story ball</name>
		<pose>Unspecified</pose>
		<truncated>0</truncated>
		<difficult>0</difficult>
		<bndbox>
			<xmin>135</xmin>
			<ymin>137</ymin>
			<xmax>272</xmax>
			<ymax>273</ymax>
		</bndbox>
	</object>
</annotation>
