<annotation>
	<folder>dataset_toy_story</folder>
	<filename>image89.png</filename>
	<path>/home/ctortosam/Escritorio/dataset_toy_story/image89.png</path>
	<source>
		<database>Unknown</database>
	</source>
	<size>
		<width>478</width>
		<height>396</height>
		<depth>3</depth>
	</size>
	<segmented>0</segmented>
	<object>
		<name>toy story ball</name>
		<pose>Unspecified</pose>
		<truncated>0</truncated>
		<difficult>0</difficult>
		<bndbox>
			<xmin>91</xmin>
			<ymin>84</ymin>
			<xmax>370</xmax>
			<ymax>355</ymax>
		</bndbox>
	</object>
</annotation>
